dui_automation/VERSION
dui_automation/__init__.py
dui_automation/da/__init__.py
dui_automation/da/common/__init__.py
dui_automation/da/common/by.py
dui_automation/da/common/configurator.py
dui_automation/da/common/decorator.py
dui_automation/da/common/keycode.py
dui_automation/da/common/selector.py
dui_automation/da/core/__init__.py
dui_automation/da/core/driver.py
dui_automation/da/core/exception.py
dui_automation/da/core/hwnd.py
dui_automation/da/core/watcher.py
dui_automation/da/core/window.py
dui_automation/da/core/control/__init__.py
dui_automation/da/core/control/attribute.py
dui_automation/da/mixins/__init__.py
dui_automation/da/mixins/watcher_manager.py
dui_automation/da/mixins/rpc/__init__.py
dui_automation/da/mixins/rpc/control.py
dui_automation/da/mixins/rpc/driver.py
dui_automation/da/mixins/rpc/window.py
dui_automation/da/mixins/rpc/window_action.py
dui_automation/da/mixins/uia/__init__.py
dui_automation/da/mixins/uia/driver.py
dui_automation/da/mixins/uia/window.py
dui_automation/hook/__init__.py
dui_automation/hook/da_frida.py
dui_automation/hook/da_uia.py
dui_automation/hook/inject.py
dui_automation/hook/messages.py
dui_automation/hook/rpc.py
dui_automation/scripts/duilib.js
dui_automation/utils/__init__.py
dui_automation/utils/frida_utils.py
dui_automation/utils/util.py
dui_automation/utils/win_tools.py
duiautomation-2.0.1.data/data/dui_automation/VERSION
duiautomation-2.0.1.data/data/dui_automation/duilib.js
duiautomation-2.0.1.dist-info/METADATA
duiautomation-2.0.1.dist-info/WHEEL
duiautomation-2.0.1.dist-info/top_level.txt
duiautomation-2.0.1.dist-info/RECORD
