Metadata-Version: 2.4
Name: DuiAutomation
Version: 2.0.1
Summary: An ui-autotest framework for windows DuiLib.
Home-page: https://gitee.com/qetest/DuiAutomation
Author: Bruce Cai
Maintainer: Bruce Cai
Maintainer-email: caibin@qiyou.cn
Classifier: Framework :: Scrapy
Classifier: Development Status :: 5 - Production/Stable
Classifier: Environment :: Console
Classifier: Intended Audience :: Developers
Classifier: Operating System :: OS Independent
Classifier: Programming Language :: Python
Classifier: Programming Language :: Python :: 3
Classifier: Programming Language :: Python :: 3.5
Classifier: Programming Language :: Python :: 3.6
Classifier: Programming Language :: Python :: 3.7
Classifier: Programming Language :: Python :: 3.8
Classifier: Programming Language :: Python :: 3.9
Classifier: Programming Language :: Python :: 3.10
Classifier: Topic :: Internet :: WWW/HTTP
Classifier: Topic :: Software Development :: Libraries :: Python Modules
Requires-Python: >=3.5
Requires-Dist: frida==16.0.19
Requires-Dist: frida-tools==12.1.2
Requires-Dist: psutil~=5.9.5
Requires-Dist: jsonpath==0.82
Requires-Dist: uiautomation==2.0.29
Dynamic: author
Dynamic: classifier
Dynamic: home-page
Dynamic: maintainer
Dynamic: maintainer-email
Dynamic: requires-dist
Dynamic: requires-python
Dynamic: summary
